__test/__init__.py
__test/test.py
__test/test2.py
aps/__init__.py
aps/common/__init__.py
aps/common/chain_of_responsibility.py
aps/common/data_structures.py
aps/common/initializer.py
aps/common/logger.py
aps/common/plotter.py
aps/common/reflection.py
aps/common/registry.py
aps/common/singleton.py
aps/common/traffic_light.py
aps/common/utilities.py
aps/common/driver/__init__.py
aps/common/driver/beamline/__init__.py
aps/common/driver/beamline/generic_camera.py
aps/common/io/__init__.py
aps/common/io/printout.py
aps/common/io/serialization.py
aps/common/io/sys_commands.py
aps/common/io/tcp_client.py
aps/common/io/tiff_file.py
aps/common/plot/__init__.py
aps/common/plot/event_dispatcher.py
aps/common/plot/gui.py
aps/common/plot/image.py
aps/common/plot/qt_application.py
aps/common/plot/splitter.py
aps/common/plot/__test/__init__.py
aps/common/plot/__test/blinker.py
aps/common/plot/__test/mediator.py
aps/common/plot/__test/test_splitter.py
aps/common/scripts/__init__.py
aps/common/scripts/abstract_command_line_script.py
aps/common/scripts/generic_process_manager.py
aps/common/scripts/generic_qt_script.py
aps/common/scripts/script_data.py
aps/common/scripts/script_registry.py
aps/common/widgets/__init__.py
aps/common/widgets/close_app_widget.py
aps/common/widgets/congruence.py
aps/common/widgets/context_widget.py
aps/common/widgets/generic_widget.py
aps/common/widgets/log_stream_widget.py
aps/common/widgets/stream_proxy.py
aps_common_libraries-1.0.20.dist-info/licenses/LICENSE
aps_common_libraries-1.0.20.dist-info/licenses/LICENSE.pdf
aps_common_libraries-1.0.20.dist-info/METADATA
aps_common_libraries-1.0.20.dist-info/WHEEL
aps_common_libraries-1.0.20.dist-info/top_level.txt
aps_common_libraries-1.0.20.dist-info/RECORD
