Metadata-Version: 2.4
Name: aps-common-libraries
Version: 1.0.20
Summary: APS Common Libraries
Home-page: https://github.com/APS-XSD-OPT-Group/Common-Libraries
Download-URL: https://github.com/APS-XSD-OPT-Group/Common-Libraries
Author: Luca Rebuffi
Author-email: lrebuffi@anl.gov
Maintainer: XSD-OPT Group @ APS-ANL
Maintainer-email: lrebuffi@anl.gov
License: BSD-3
Keywords: dictionary,glossary,synchrotronsimulation
Classifier: Development Status :: 4 - Beta
Classifier: Environment :: X11 Applications :: Qt
Classifier: Environment :: Console
Classifier: Environment :: Plugins
Classifier: Programming Language :: Python
Classifier: Operating System :: POSIX
Classifier: Operating System :: Microsoft :: Windows
Classifier: Topic :: Scientific/Engineering :: Artificial Intelligence
Classifier: Topic :: Scientific/Engineering :: Visualization
Classifier: Topic :: Software Development :: Libraries :: Python Modules
Classifier: Intended Audience :: Education
Classifier: Intended Audience :: Science/Research
Classifier: Intended Audience :: Developers
License-File: LICENSE
License-File: LICENSE.pdf
Requires-Dist: setuptools
Requires-Dist: numpy
Requires-Dist: scipy
Requires-Dist: numba
Requires-Dist: matplotlib
Requires-Dist: AnyQt
Requires-Dist: scikit-image
Requires-Dist: opencv-python
Requires-Dist: h5py
Requires-Dist: torch
Requires-Dist: pyepics
Requires-Dist: pvapy
Dynamic: author
Dynamic: author-email
Dynamic: classifier
Dynamic: description
Dynamic: download-url
Dynamic: home-page
Dynamic: keywords
Dynamic: license
Dynamic: license-file
Dynamic: maintainer
Dynamic: maintainer-email
Dynamic: requires-dist
Dynamic: summary
